{
"type": "FeatureCollection",
"name": "ANTENNE",
"crs": { "type": "name", "properties": { "name": "urn:ogc:def:crs:OGC:1.3:CRS84" } },
"features": [
{ "type": "Feature", "properties": { "id": 1, "TITOLARE": "WIND TRE SPA (ex H3G)\n", "UBICAZIONE": "VIA GATTI 57\n", "UTILIZZO": "ANTENNE TELEFONIA\n", "CONTRATTO": "DIRITTO DI SUPERFICIE\n", "DURATA_CON": "TRENTANNI\n", "SCADENZA": "2048\n", "VAL": "79.200,00\n", "SUPERFICIE": "50 mq\n", "TIPO AREA": "terreno \n" }, "geometry": { "type": "Point", "coordinates": [ 10.264989432882205, 45.52199471802934 ] } },
{ "type": "Feature", "properties": { "id": 2, "TITOLARE": "WIND TRE SPA \n", "UBICAZIONE": "VIA COLLEBEATO\n", "UTILIZZO": "ANTENNE TELEFONIA\n", "CONTRATTO": "DIRITTO DI SUPERFICIE\n", "DURATA_CON": "TRENTANNI\n", "SCADENZA": "2048\n", "VAL": "88.000,00\n", "SUPERFICIE": "46 mq\n", "TIPO AREA": "area demaniale\n" }, "geometry": { "type": "Point", "coordinates": [ 10.207635022510045, 45.563139819558266 ] } },
{ "type": "Feature", "properties": { "id": 3, "TITOLARE": "GALATA SPA\n", "UBICAZIONE": "VIA MUSIA\n", "UTILIZZO": "ANTENNE TELEFONIA\n", "CONTRATTO": "DIRITTO DI SUPERFICIE\n", "DURATA_CON": "VENTANNI\n", "SCADENZA": "2037\n", "VAL": "82.500,00\n", "SUPERFICIE": "45 mq\n", "TIPO AREA": "area demaniale\n" }, "geometry": { "type": "Point", "coordinates": [ 10.288687581277284, 45.513764297507031 ] } },
{ "type": "Feature", "properties": { "id": 4, "TITOLARE": "GALATA SPA\n", "UBICAZIONE": "VIA ORZINUOVI\n", "UTILIZZO": "ANTENNE TELEFONIA\n", "CONTRATTO": "DIRITTO DI SUPERFICIE\n", "DURATA_CON": "VENTANNI\n", "SCADENZA": "2037\n", "VAL": "82.720,00\n", "SUPERFICIE": "40 mq\n", "TIPO AREA": "area demaniale\n" }, "geometry": { "type": "Point", "coordinates": [ 10.173632052523036, 45.535571184447981 ] } },
{ "type": "Feature", "properties": { "id": 5, "TITOLARE": "INWIT SPA\n", "UBICAZIONE": "VIA 13a Q.RE C. ABBA,22\n", "UTILIZZO": "ANTENNE TELEFONIA\n", "CONTRATTO": "DIRITTO DI SUPERFICIE\n", "DURATA_CON": "VENTANNI\n", "SCADENZA": "2037\n", "VAL": "95.000,00\n", "SUPERFICIE": "14+18+95 mq\n", "TIPO AREA": "lastrico solare + area\n" }, "geometry": { "type": "Point", "coordinates": [ 10.194912221399179, 45.562926696797135 ] } },
{ "type": "Feature", "properties": { "id": 6, "TITOLARE": "INWIT SPA\n", "UBICAZIONE": "VIA MAGGIA\n", "UTILIZZO": "ANTENNE TELEFONIA\n", "CONTRATTO": "DIRITTO DI SUPERFICIE\n", "DURATA_CON": "VENTANNI\n", "SCADENZA": "2037\n", "VAL": "88.000,00\n", "SUPERFICIE": "41 mq\n", "TIPO AREA": "terreno \n" }, "geometry": { "type": "Point", "coordinates": [ 10.236977283900986, 45.510893655676078 ] } },
{ "type": "Feature", "properties": { "id": 7, "TITOLARE": "INWIT SPA\n", "UBICAZIONE": "VIA STASSANO\/VIA SERPENTE\n", "UTILIZZO": "ANTENNE TELEFONIA\n", "CONTRATTO": "DIRITTO DI SUPERFICIE\n", "DURATA_CON": "VENTANNI\n", "SCADENZA": "2037\n", "VAL": "44.000,00\n", "SUPERFICIE": "41 mq\n", "TIPO AREA": "terreno \n" }, "geometry": { "type": "Point", "coordinates": [ 10.156307817666496, 45.50806466630241 ] } },
{ "type": "Feature", "properties": { "id": 8, "TITOLARE": "VODAFONE\n", "UBICAZIONE": "VIA CIMABUE, 18\n", "UTILIZZO": "ANTENNE TELEFONIA\n", "CONTRATTO": "DIRITTO DI SUPERFICIE\n", "DURATA_CON": "TRENTANNI\n", "SCADENZA": "2048\n", "VAL": "99.000,00\n", "SUPERFICIE": "41 mq\n", "TIPO AREA": "lastrico solare\n" }, "geometry": { "type": "Point", "coordinates": [ 10.258924294406569, 45.516664406032525 ] } }
]
}
